src/__init__.py
src/app.py
nfs_estepona-0.3.0.dist-info/LICENSE
nfs_estepona-0.3.0.dist-info/METADATA
nfs_estepona-0.3.0.dist-info/WHEEL
nfs_estepona-0.3.0.dist-info/entry_points.txt
nfs_estepona-0.3.0.dist-info/top_level.txt
nfs_estepona-0.3.0.dist-info/zip-safe
nfs_estepona-0.3.0.dist-info/RECORD
