Metadata-Version: 2.1
Name: nfs-estepona
Version: 0.3.0
Summary: a simple CLI tool to split a file into several smaller chunks at data level and merge them back
Home-page: https://github.com/estepona/naive-file-splitter
Author: Binghuan Zhang
Author-email: esteponawondering@gmail.com
License: MIT
Keywords: CLI,file,split,utility
Classifier: Programming Language :: Python :: 3
Classifier: License :: OSI Approved :: MIT License
Classifier: Operating System :: OS Independent
Requires-Python: >=3.5
License-File: LICENSE
Requires-Dist: click
Requires-Dist: tqdm
